algora/__init__.py
algora/api/__init__.py
algora/api/data/__init__.py
algora/api/data/fred/__init__.py
algora/api/data/fred/__util.py
algora/api/data/fred/asynchronous.py
algora/api/data/fred/model.py
algora/api/data/fred/synchronous.py
algora/api/data/iex/__init__.py
algora/api/data/iex/__util.py
algora/api/data/iex/energy/__init__.py
algora/api/data/iex/energy/__util.py
algora/api/data/iex/energy/asynchronous.py
algora/api/data/iex/energy/synchronous.py
algora/api/data/iex/stocks/__init__.py
algora/api/data/iex/stocks/__util.py
algora/api/data/iex/stocks/asynchronous.py
algora/api/data/iex/stocks/synchronous.py
algora/api/data/query/__init__.py
algora/api/data/query/__util.py
algora/api/data/query/asynchronous.py
algora/api/data/query/model.py
algora/api/data/query/synchronous.py
algora/api/data/sdr/__init__.py
algora/api/data/sdr/__util.py
algora/api/data/sdr/asynchronous.py
algora/api/data/sdr/synchronous.py
algora/api/service/__init__.py
algora/api/service/admin/__init__.py
algora/api/service/admin/__util.py
algora/api/service/admin/asynchronous.py
algora/api/service/admin/synchronous.py
algora/api/service/auth/__init__.py
algora/api/service/auth/__util.py
algora/api/service/auth/asynchronous.py
algora/api/service/auth/synchronous.py
algora/api/service/backtest/__init__.py
algora/api/service/backtest/__util.py
algora/api/service/backtest/asynchronous.py
algora/api/service/backtest/enum.py
algora/api/service/backtest/model.py
algora/api/service/backtest/synchronous.py
algora/api/service/data_engine/__init__.py
algora/api/service/data_engine/__util.py
algora/api/service/data_engine/asynchronous.py
algora/api/service/data_engine/enum.py
algora/api/service/data_engine/model.py
algora/api/service/data_engine/synchronous.py
algora/api/service/dataset/__init__.py
algora/api/service/dataset/__util.py
algora/api/service/dataset/asynchronous.py
algora/api/service/dataset/model.py
algora/api/service/dataset/synchronous.py
algora/api/service/dataset/abstract/__init__.py
algora_sdk-1.5.39.dist-info/METADATA
algora_sdk-1.5.39.dist-info/WHEEL
algora_sdk-1.5.39.dist-info/top_level.txt
algora_sdk-1.5.39.dist-info/RECORD
