Metadata-Version: 2.1
Name: algora-sdk
Version: 1.5.39
Summary: Algora Labs Python SDK
Home-page: https://algoralabs.com
Author: Algora Labs
Author-email: hello@algoralabs.com
License: UNKNOWN
Platform: UNKNOWN
Classifier: Programming Language :: Python :: 3
Classifier: Operating System :: OS Independent
Requires-Python: >=3.7
Requires-Dist: PyYaml (==6.0)
Requires-Dist: aiocache (==0.11.1)
Requires-Dist: aiohttp (==3.8.1)
Requires-Dist: asyncio (==3.4.3)
Requires-Dist: cachetools (==5.2.0)
Requires-Dist: fastparquet (==0.8.1)
Requires-Dist: msgpack (==1.0.4)
Requires-Dist: numpy (==1.22.1)
Requires-Dist: pandas-market-calendars (==3.4)
Requires-Dist: pandas (==1.3.5)
Requires-Dist: pydantic (==1.9.1)
Requires-Dist: pydash (==5.1.0)
Requires-Dist: requests (==2.28.1)
Requires-Dist: scipy (==1.8.0)
Requires-Dist: ujson (==5.4.0)
